{
"wugizf7ohdr25q6oxxoxulg6":["fatstackman","itmemary"],
"4agrpt5unyidgyqbyf3qzpdt":["itmeharu","Haru!"],
"6i76ess6n5gq4noaefq5ioyl":["itmeanspencil","pencil"],
"fam7k6beac6tpmf7i6lv735k":["itmeporps","It Me! Porps"],
"hpepvgf3tls7x7kegndvmjug":["itmakesyastrong","Scarebear Roy of Cult Cinema Catacombs"],
"jbobcyshfpnjjqr2ap6yqefg":["itmejp.com","itmeJP"],
"rxp6cbwbebsz7tpacgg2gq6e":["itmustbebunnies","🌿Fern🌿"],
"ut5cqlsxxhkhb5yvmg34wfhc":["itmecraigy","Craigy ✨"],
"wlgts64bq7hpgvj3q2hccaul":["itmearby","Arby"],
"yenje7y4bubvjdw2jqrkgpvv":["itmaybejay","Jay the Work from Home Astronaut"],
"c7jmijvmeff5cmiof5haaks5":["itmel","Elahe"],
"gyvksox4lrd7rwqubf3ljdgk":["itmebrain","₿ryan"],
"23ghtksspdsuqvxaqthdiz6c":["itmzk","110"],
"ctebakow6nlmfc4ggbmtrbgu":["itmahdieh","مَه"],
"hqgqqbeiawlhxucth3xi44we":["itmanuel","Manuel"],
"fvqohqmkx5febdw2fb4gecci":["itmeansunique","Unique"],
"oxfbc2n6rnqfoqwoltbso62m":["itme813","NBB"],
"tbwtniz4mkxuep24x35tt5cj":"itmeanstoimmerse",
"bkgu6tlkxzib4nomwyntutje":["itmelted","에오"],
"trogk33rhvryuy66stziuu3f":"itmightbejimbo",
"jfpjmjgmkyr7t4zosm4j6ume":["itmejd","JD 🏔️🐐"],
"b5kogqw6yzwjfwhduoubrrr3":["itman","MG"],
"rml6jv7ew7gwkspdq36mxxen":["itmehassan","Hassan"],
"nucjlqvj5cv4vzldv3hveeg5":["itmestan","Stan Press 🇺🇦"],
"n7hhei2nfrnqqjbvcnquw7t4":["itmezaack","Zack"],
"wxyiezkhk26w576svr2w4d37":["itmeobed","europhobe"],
"px3amfyfzentbu5gk3raqv2c":["itmabi","Maria Beatriz"],
"zdmt4ihuupjjb55foq4ga2dj":"itmahak",
"qweho43ziox5v3jt73endfg4":["itmegetabeer","Vogon Love Poetry"],
"3jeugtqlncmrtyoomw6g3rdg":["itmightbemikey","it might be mikey"],
"qmgwda6o6zkeaet47aawh3r6":["itmecadabo","Advanced Dungeons and Dadbods"],
"gxutowmduwrqnbdbe4dal7vd":"itmustbeguv",
"xmu5eag5tuaatjplt4pczyts":["itmnrg","ともぞー"],
"pce775lpi3fyswot4cthymcz":["itmeelo","Nathan Xa"],
"x7v7gwe6zmvmdk773q4quucn":["itmeolliev","Oliver VanDervoort"],
"r3ijauga3mtzy4p36vh3kdf3":["itmecarter","Carter H"],
"vcovd2jouzjkef2xjto64fds":["itmatheus","Matheus The Arrogant 🍏"],
"zbwt5upujnnj5tn5dvqubgom":"itmeavery",
"fqnjpv5oeqbnmfoqyccesi2b":["itmewrex","WreX"],
"t4ioqrmvxbyqdqiyrgmhwgpg":["itm4n","Clément Labro"],
"kmmp4ef2j6vdgnvujrannt4i":["itmejaviri","Javier Riera"],
"bgiybnugyeugosx72qsoi2aw":["itmefloofy","! Maybe Milk !"],
"b42sv7ncgomt6taaxjljvmrl":["itmerobin","Robin"],
"5ibl4dstssosnlg4xz3tpy57":"itmeeric",
"mmqliq7b7dtsq33j7hnddgzf":["itmearioid","Ari"],
"isn3oehva77isnafcpupyxb4":["itme","ItMe!"],
"skivmczkfoo3s36pb4iv22fs":"itmesunflower",
"4dln5rhjp25loasohv4yg2ug":"itmechestnut",
"6u6xv3jdhrxkwezzbygsj2uk":["itmebugail","Abigail Finch"],
"fxe43khhg3xb4s34zk33teft":["itmeshock","Ashe"],
"opckd2cuwu3mduic42n6idst":["itmeftm","Fateme"],
"vxi2nuynkm6jpv33gpeje2gt":["itmeanswhatitmeans","It Means What It Means Podcast"],
"e76tcieoaljje4xlpmtiig4h":["itmesarly","Sarly"],
"efr5gomurig66tvndaw5ei2b":["itmaroon","M.ar.oon (Commissions open 0/2)"],
"lyhjdck263p7wqks4qllm6ta":["itmightbe","What"],
"57goe4ylh6ev6xaxlbrakwph":["itmeryand","RÝÄÑ D"],
"bg247fppbkthhilvkcgzzxaa":"itmetch",
"2lr4alytaybylwhhe65dqjlj":["itmedoofy","🕷️ The Spookiest Yeen 🎃"],
"sdwkbadvyaulbbhiwq55quhm":"itmorar",
"g2fvb2ti7piruw5f75otcjh7":"itmelarry",
"ohptesgiu7r4xgrdyczvwcti":["itmepz","PZ"],
"6iywu66z6nwi3ja5wb5sbw4u":["itmustgetlonely","brynne"],
"hkpz3mvopkn2jihlsaci4jgw":"itmoon9",
"2zsuhwdnbjrjoxr3vilcwolo":"itmedb",
"sedlgfwzkrn5mcljlujoqzdp":"itmekennedy",
"4vwz6itu23n5fqngk4mvpth5":"itmaluhs",
"abthjj2wlkbztnufwhqbeylr":["itmechris","Chris__t4"],
"rwu3xthyzogpdqfxa5kd4fnd":"itmegog14",
"h56cjqnk5tn7c3744ctsnwrx":"itmelol",
"saoyk3vuxzelaspy33l4ms5l":["itmemorgan","Morgan"],
"v5ihg3hgcc6ys3ggd22g767a":["itma","James Scott of Ugie"],
"pw5po5fwqw6dfnai2jrjzdts":"itmightbesean",
"jct2leewniqegbcydpqm2fzd":["itmo","itmo"],
"5aptlwav5mv3o5pqwkpdpsp3":["itmenoah","Noah"],
"dul2fyoupl7x7dygwu7vygeh":["itmejordan","Itmejordan"],
"ruvbgz4dhyr4xy7parq2ylrx":["itmecathy","catherine"],
"hifdemhhqwmbzbkxi4udb6bx":"itmegog2",
"vwa42uzx7gadce7s2ey2zl55":["itmesully","Sully"],
"7bdqxbp4cxgggp5bn2wsbjig":["itmecody","Cody"],
"kgcq7fea5gmwhxvizkcpcuh7":["itmg","i tee em gee"],
"xpwedo6zerstuc2p7icypof7":["itm","itm 4.0 "],
"rerobio3eyrtlc5fobwcynzs":["itmyad","Itmy_AD"],
"gh2q7feg7m5zbvdlz5ifaxee":"itmecait",
"eo7bfc5v6tffj26nlew4kegg":["itmoonhere","månen"],
"va7x2xm2avfcgqyxuxb4ng6s":["itmedami","itmedami"],
"srbo4uq4ibe5i325bnj4iztk":["itmight","It Might Be Vidiot"],
"aztm47y5mjp34okdenxlmkvs":["itmesleepy","ItMeSleepy"],
"ob46k2qz42w7ws3cqds3aqln":["itmetai","ItMeTai"],
"ohrvl57uesfxou3qajdwbn7x":["shownomercy","itme_lonmusk"],
"mijceelttrt3y3x23ixhqriw":["superbeaualpha1","itme "],
"5rdy4onmaajnkopurosbm7ip":"itmehyuri",
"eojio2js7h3qwumatpwyttxx":["fraunhoferitmp","Fraunhofer ITMP"],
"pmszoy4vxoiwlc6mawzweuln":["itmeuka","うか"]
}
