{
"hiudybihlhjmd24rg734hxky":"32inbluesquare",
"4rueinuigvvspwke4dld4zth":["22inbloom","Bloom"],
"quldil7q5mbepaxo4x5w6ika":["asianinbound","AdrianInbound"],
"zuyp4cffwoytm5pzhzv3nsv7":["bittybatarts","Little fucking thing inbound"],
"au5j6eufccyvderjxfrxxkb5":["canglong333","Cang Long, aka He’s Not an Inbred Moron"],
"g4yoet3izcrkeebgwgtomklb":["clownpackage","Inborn Openness"],
"flycozkhuf6pgzlqvylxn5kc":["fluxvector","flux❌「redebut inbound」"],
"s4wakd55lggrjqydbmut52ft":["greyannis","Inbal Breda"],
"eg7jfu7e7a5eae6srj43zxub":["hotkraftsingles","hot kraft FEMA ALERT in your inbox!"],
"qgm6nbqov5vcz34bsjn5q4ql":["idnotinuse","Inbam"],
"fdvpodxyqgq66k52mi7eewgp":["inbee","Inbee&D"],
"fxrkdkatt5fcsrtve5dqtfhc":["inblossom","inblossom"],
"nfhkj5dnynynmsivxjl4i6aa":["inblue","alexa"],
"p7vqevgjwabyxakzljehovll":["inbedwiththeright","In Bed with the Right"],
"uaz56rf42h4ibxgt67bgzho6":["inbellaland","Bella "],
"uams2ogwxcro4ccjgy3umyow":["inbhirnis","Roy MacPhail"],
"acybuivyredbwkqy4mgxlkms":"inboots007",
"dcstjvouq4w5h2evenekb3sc":["inbetweencosmos","RAY"],
"lxu4jwnp6zl4ji2pyvc63s3h":"inb4",
"mmgdlv6vc6y5rna3xafb4bjw":["inbalboa","Сергій"],
"cuehaosmqpklwzol4tzprgpw":"inbloom",
"lsd634xtr2htuydk6xjbdx4u":["inbradtaste","Brad"],
"opcx7hjnxh5ybtjyzeqbzrsn":["inb4iba","Icaro \"Iba\" Andrade"],
"7nkq2gpixjgwtwu3aotwbad6":["inbeehive","蜜蜂。"],
"aguyp3tiqgmhynhd4dkmcxr3":["inboundike","Inbound Ike"],
"crwfhkc7m6yu5dazq2ykcvac":"inbok",
"yowx5cjgtl2ysn4hnophcyzg":["inbeom.com","inbeom"],
"skmupqzm4ff2awr4aaitdxat":"inbottom",
"nsxlsuu6ehgrggdar325jj66":["inbarshoham","Inbar"],
"tmennmno2tgnyblxbe4bacch":["inbox5372","72fcosta"],
"lqpgzxuooby2iruckjndqqvx":["inbarbiewordl","barbie do proletariado 🩷"],
"zxotj7rnlivsamqomrokb4kz":"inbarigami",
"ovosl7ladcxp4zsej3vc4cw5":["inba","印旛"],
"ejafes4vkhmptavnvwsjjuqq":["inbryanwetrust","Bryan"],
"gcbz7lrwc26ikruiihysyghl":"inbeda",
"chsv7up7axi5oi2esmumzpke":["inboxraj","r@j€sh"],
"regxwlferxiuyogrhshyvcb2":"inbx",
"gylkmxoufcy3bejupsl4ccix":"inbadluck",
"fnkxfkpx32w5dkpm4itegepq":["inboundlee","Lee"],
"hkumy6t35zh4ixxd5jt6nxcu":["inbaeda","Inbaeda 🕸️"],
"bqnf3omsfcuza5mgyckr5tlj":"inb4bread",
"2xmgwfncs2rkua2nwifebb4f":["inberlin404","404"],
"5pv6f4lj235ve4auvapacdcb":"inbare",
"f5kmqb72ovdu4a3unnuqumvx":["inbetween777","✨"],
"bnw26o4jz4uxhuoi2mpso6vc":["inbetween","dazwischen"],
"owolyecxqknxl4k2qrvfqtff":["inballonx","InBallonx 🆒️⚖️♥️"],
"tqdahegd3ir2np2qvwwg6qby":["inbetweener","Inbettwiener"],
"ga7su4hlerr23xma4vhhojdr":"inbal",
"w4m7mprhcogd6jztgk7kvn7q":["inbalharding","Inbal Harding "],
"6haxnpqpt6bfv4lpyxhybnm6":"inbibiitrust",
"joaldc26vb5cw2tymgj4iewm":["inbroso.de","Marc - inbroso"],
"syydyg3r6vqiqjk26kbq5lok":["inbottomdrawer","Bottom Drawer"],
"dpbmz54ly63pffx7xu5czjzy":"inbluelook",
"nmpbw6pduimhkyxhvjchezk2":["inbaeca","Inma "],
"xtv5d5xkcogzndxmfmmnzz5b":["inbaleg","inbal"],
"e3wlvjgf4ytyxziewum5t7sa":["inblossom4kate","Kay Tea "],
"eg22gloldv4i76bazxsyw2co":"inbetweenacross",
"dfnd4lfib33lrvi4lew2ibxk":"inbtwn",
"ypwew4my72dh4r22n6yczo2e":["largenagainbound","LargeNagaInbound 🔞 (No Minors)"],
"pckd6zhxeig7kngqijbpg5em":["lifeform","inbox"],
"sgjuweigkoymllbbnumaxbmv":["naughtyroomba","Roomba 2.0 inbound | vTuber | ルンバの振る舞い"],
"drwzhoggkwgfgdbephkovpjo":["phoenix-inblue","Angelaun "],
"lbow2yc3urabk5xjsytbbaqe":["r4inbowtail","Red \"RedPup\" Rainbowtail"],
"yo3apgqipq6de7lj6cfpbpge":["yoelinbar.net","Yoel Inbar "]
}
