{
"6u7jhkhg7rzjtogfoxu5czh5":["annunddie","Ann und die Igel"],
"sz77yktieeszjew7nstoakw2":["arisquetaigea","Javier Igea Arisqueta"],
"5umyumjmycrutryxjwjqet3h":["bhsbaby","OhGodHowDidIGetHere"],
"lf6mnviltfpvwi2f4veyyzzh":["bradleyiger","Bradley Iger"],
"fw2l73lf75ezk3qlypkebeup":"chimes-igen",
"brdnbq7cjgujhrgn4krxv3zt":["dalemunk","Igelkotten Konrad"],
"qtjpe47p7h6cycpvfshamdda":["dasigelchen","Igelchen "],
"r7hysygobtw7yaxf52rpthwb":["dr3igeteilt","Dr3igeteilt "],
"bcuiv5urwue6gzviwnpyp5ju":["fauli","Faulenz der Fleißige"],
"j3nmzr3jfrr5wpr4dbqs7ofy":["flaumig-igel","Заїбусінка"],
"kjvgobrmbwwrxeakkdzprhgh":["flywie1igel","FlyWie1Igel"],
"zp26ehzqtpltspk4snna6krm":["ichelchen","Igelchen "],
"2yki4m5en3cevopiqt77y2ql":["igelchen","Ara Ara Delevigne"],
"uhcicbcuay2aqtwh6ukl27at":["igeligalore","igeli"],
"3y7spnv64xtzeoe6ju7ewa6j":["igel","Luke Igel"],
"7tkow73ytp2fzea6xz5pmo4i":["igeros","Ígeros"],
"hkijv7rmz2e5umpfghf5ujd5":["igestalt","iGestalt"],
"vr77uaccffamxino5kppfynr":["igetallnumb","Shan"],
"5ba47q7teroy6pqmomplofai":"igedamoya",
"lgpzcz3dvs6rysg67kxx6i2o":["igerion","Та тоТа то"],
"rsshes5aalcaivpzcxzhldw6":["igeru","Igeru"],
"ktg7jgzrfcwd23qmwitrzdpe":"igeek",
"kbhhuavikfmedfi53rthtf4l":"igerstel",
"jgzzdkakroq2dml4gzskcujw":["ige","IGE/"],
"3wh5fw64zc5tlruhda4yytlh":["igetchestpains","lars von ulrich"],
"m26qzqr7eyh2ndbtfhztoad3":["igeerb","Gerb"],
"ywqhv3ihnbd6yo6wntcw6drn":["igerrit","iGerrit"],
"2pu2yhzcdq6dha2i7let5s6q":["igerman","German"],
"yhmlq2hyqs5tuckqez4xxn6d":["igelmaedchen","nordseefuchs"],
"o3zumf3n4gcag42wawlflytl":["igelich","Igelich"],
"uqyeyfyumcdbtyigumddhd7u":["igelschnaeuzchen","Igelschnäuzchen"],
"jmh5fpylq4yqoal47hzfppxs":["igelpaul","IgelPaul"],
"yrgixjl2bildqoor7v7idoyg":["igeuer","igeuer"],
"svma2ivojyzittanvvbjrhpx":["igelfamilie","Familie Igel"],
"tocw5hevhgsefh4iv3gxsndv":["igerardoo","ger"],
"cff2e6ie2dayhlx4xwfb5q3b":"igelhans",
"nu3rjshjkg6phxhfsshvsehm":["igetdowowon","I Get Uuup"],
"d4f4uqlgfxfieb2qncrepx7z":["igeb","IGEB Berliner Fahrgastverband"],
"lni43mz4262doewgdcdnv272":["igelnase101","Igelnase"],
"v254vtgp2al4h64rn64chaf2":["igeyorhm","Igeyorhm"],
"3gvssdilz42hsibmol3walfr":["igelmarius","Bewaffnetes Meerschweinchen a.k.a Autschmaus"],
"iusch6p4fcotzvmtdiwo7u6s":["igetaro","いげ太郎/IGETARO"],
"67kvj5o7zrdwhy2fwh25zro2":["igetsoscared","Felix"],
"32ngnhrcv3gi6hcnsckvrvpo":["igeugulbe","리틀섹시퀸🥟"],
"luyncbeuxmstlelux6qhr63j":["igerwariden","Iger_Wariden"],
"lnwc77o2lsedkgxqin6vjbjy":"igederunning",
"5twas476axnqrhqi5rsy74gx":"igetmadsometimes",
"vkeneltb6egmcupvx5obapgg":"igelkott",
"jslztwuy4kp5gzq6xbdf4owp":["igerg"," IsabellaG "],
"tp2goqf7f2h5fzlcymmi5l5b":["ingridsdotra","Besynnerlig igelkott"],
"akr4ogylfku4e5hdvovmxt6z":["kathischleussig","Die Schleußigerin 🏳️‍🌈"],
"74mvuy37dvt57b6yqmpwwlei":["kigde","Klaus Igel"],
"pbxz2c5gj4yptopmeuo4go3k":["nebengleis","Verhältnismäßiges Lämmchen"],
"ycrwyzzjzwm4tvc4z75wdj5j":["profigel","Christoph Igel"],
"nzvsok5b2ackic77dc3xhtu3":["ralphigel007","Ralph Igel"],
"daiggsppnuhcmumvicewzyz7":["rigelstar","Igel"],
"jikhoee3nd26wyhw4mtjcwna":["sebastianigel.de","Sebastian Igel"],
"s3glujxgpq7r4a4dfn7ksrhy":["stacheltier","Igelchen "],
"y2yqur5y4e2cclo5zh7y62m2":["teacat","IGEL"],
"l57ql3scxxsicm35tfkb5fno":["tobos","Ein Igelu"],
"pulbdrai7voqacuus5yjvngj":["tschaeiges","Tschäiges"]
}
