{
"pkidlxb77sgqidif7xyi6f6r":["damonvonvolger","Mr. Idgafon"],
"d3jz2uu3mupxkvkc3hfdjhqc":["idguy","Bob Levine"],
"klejnyy466kcp2a4su4b2j4v":["idgordon","Ian Gordon"],
"j7jmk4rxaplb24eiapm5lf5l":"idg10",
"o7kgbvj7ufqk6ae2iupdxy2c":["idgvv","베르뱃"],
"jrqgkqu4qmsqz4q4q6ecasvv":["idgaf","Dan Fhartman"],
"udegdvfrfq5c2wjdmqgbf7rm":["idgnicholson","Ian Nicholson FRSA"],
"rhpidfi4j37mfdprty5iwmhy":["idgafaa","idgafaa"],
"5bgkxt2idv7gddsroj5c25wo":"idge",
"wng3fx74cqxe3h2w6tyqusqu":["idgpharma","Le CCA pharma bonsoir!"],
"zjeoxi5qw7zhtlputpnqkr54":["idgamingfederation","Id Gaming Federation "],
"hckaopcx2bqni6aztdvpgpzv":["idg","Ibby / IDG ✨♥️"],
"u3tyl6buqikw4vyjd5hgt2cp":["idgie","Idgie Threadgood"],
"727eerldvqamsojzs55kosd6":"idgie123",
"236rckkghc37tmggabvfo2y6":["idgiebari","Idgie"],
"uwtacw3maj3ktk4xb5sizh4m":["idgrindhaug","Medio@idgrindhaug"],
"kgw7f54zbbxftnfsriydbyz4":"idgiethreadgoode",
"mn7qnsuwyffhj4eza4ajkvmv":"idgit",
"zwzfdrbpds2i3kf2jebt5ufj":"idgi",
"wg7imrmlzk5oweb4exl6p7hc":"idgreen",
"oxvmqs3lkcuyapc7jpmncbca":"idgeek",
"dw3iaujtdw2ny2gmzpzcqcrq":"idgarabert",
"wp5c7jmkypu4e5oxaosrpzva":["idgdraken","Draken"],
"y4ttsexgi55h2wf2ai4hllqd":["lilsus","Idgaf war vet"],
"mdnmhgecbgjj3mjzhjjc5w4g":["mallowmassacre","Mallowrie Malloi 🌒🔞🌘 drowTuber ✨ idgaf era ✨"],
"numt2lkazyzuwllho7ho7ve7":["originalidgie","Idgie"],
"dkohkuinbdppr6rbr3etatkl":["senpaidgaf","SenpaIDGAF"],
"d57yvzk4mkttrechmmu2c54k":["selchingtime","♦️Idga Tepes♦️"],
"a67qyclfk6cfunzpafgz4sx4":["yumechuyume","phoenix hero of the idgaf war"]
}
