{
"eu7mstgbkdbw6lsvlxfq73z4":["emperipi","Emiliano Perez Ipiña"],
"dzibhbrlkrddsgufsh532vue":["ipizza666","IlluminatiPizza666"],
"jgdoaoedeuoq5fzvtdn6ynkw":["ipitythemule","mule™️"],
"pqqdeg4dmjxlu7yqn4dlzjke":"ipiskunova",
"4ehfm2ulawxjpmy3i6utwy4x":["ipitacio","Ipitácio (Thunder)"],
"noofu4bxgf7gdiubfcjdahnv":["ipitythefoos","Stable of Stars 💦🥩"],
"dbatrz3c36dik72ejkfzrz2z":"ipickbadusernames",
"phhxnjr6hzgkltvheag6lvns":["ipilko","Ian"],
"bxnuxv72zqby3k4eyys4upgo":["ipi","ıpı"],
"nxioxcmamxoz33llztb3b7cc":"ipinpin",
"smxxwrfky26uvjsqtcgx6cc5":["ipillyc","Eagle-Owl 🦉"],
"ear7pcmdxfq77ayb7mkwrwcl":["ipixelgalaxy.com","iPixelGalaxy"],
"be7q76vhk4uar5laz5gikhua":"ipinions",
"oxxquhcohhfqded74zj3ccxc":"ipickuppennies",
"l6cxhngfg7fcag6bnihcceqn":["ipid","Ipid"],
"ntgqhjprdtnkvr2gka3bsl2f":"ipissinlitterboxes",
"2u3b3hhw64g5xtzwz67ad2no":["ipipo","Ipipo"],
"c33uaja4glka5xy6e37vbb6y":"ipippi",
"jbqgxe5s7t4t3rdzrl7lpt5g":["ipiauensis","Deuzémais"],
"xaamwamehlizytxuac57a7xq":["ipiranga","IPIRANGA"],
"j2d2ex44gl4byh7tjyartyjn":"ipifarre",
"rpn4u3ca6yld5adynz7yal32":["ipinkkherry","★Kherry★"],
"d6fj5dmjqwbj5cg7lrdu6yk3":["ipistachio","Pistachio"],
"oxlbf4frguzwm7d5znn54deo":["ipink","ipink"],
"4thq2qqq24f25dlhpt3unpk7":"ipiet",
"4jjojzckvbcna2f44m77atga":"ipirez",
"tcfv5nf5jl67la4mb5bnvjfu":"ipijda14",
"i75ug7jjoz7v7yjmw5dw7rhk":["ipirat1","JosepH "],
"hkrjnmrqayjqlfmcghxtkkp7":"ipijda10",
"ebybhnn3tdjd6scljw2upmuo":"ipijda16",
"que7pxbwqyrr663cvh3mjtlq":"ipie4fun",
"flu5rn2xbpqws4mohtcnxxin":"ipinchemajo",
"uhnboptsezfqw4geu5ohlps2":["markusraipio","Markus Räipiö"],
"cmxfx4jgt5bopen4s6cczfyo":["r0ttenapple","依蘋IPIN"]
}
