{
"uabo6ezyinahawjtpsvphx6g":["bippelle","the ipod brothers"],
"xcsqnpmvurgjg3jwkixaotue":["fluctuatnec","Fabrice & Gulliver & Ipolyte 😻😻 "],
"digciwqb7rhgaxvi5oxpjfoa":["ipoof","iPoof"],
"jsa5uh6tyvwp7dqz7ypsm6av":["ipodschun","Derric Podschun"],
"m5tjtg7lny7ofx3baxtlneiz":["ipowell","i_powell"],
"pgdoe67kzvy62ftgalzy33iu":["ipoe","ina"],
"uxp34fh34rbnyddqeulvc4fr":["ipolldata","Jessica Ko"],
"vrsbxalj7eobaet5mmchnx5k":"ipomoea",
"wrxnnftwykcn63heixx35e4r":["ipokoumeya","𝓀ℴ𝓊𝓂ℯ𝓎𝒶 ☆"],
"yhsz5yuxhjhhnhn7h62jpkce":["ipolojac","Ivan Polojac"],
"xzn2zzarrq7wbphcpbcm3g5a":["ipond317","Ian Pond"],
"jmap3sawgqshuyehk5zua7ll":"ipolit",
"eiiabnh7l5sbswml5kqvzybs":["ipoga","Jens Peter Andersen"],
"3sxuexaa4eu3kqbtnfcxwyql":["ipodstyle","iPod Style "],
"55hqczqtdmv36ywaxqpzyi7v":["ipoo","イプー"],
"34cfk2hifjrnthmyuv522odq":["ipouria","Pouria"],
"odsjlwoyhejk3hwl537dsfse":["iposs","Alexander Posselt"],
"aicos2yuaoswi6yt2a5bmg6x":"ipooya",
"5bamoooaz27whxspqahi5mlt":["ipod","Pod"],
"5tmpctx22id542lohptv7yte":["ipodnana","ipodnana"],
"6zrv7w6ry4zfph56br2hxame":["ipoundpuppies","Darnell Hot"],
"o47ehn6p66aijzrfzoqao6c3":["ipod-linux","carlos"],
"o65mdprjchs2by52cj6cqb3b":["ipoarch","Isaac"],
"prjl4zexvmkyomuwueradmom":"ipower",
"mwvbfpwho3um6uq7l7hbb67u":"ipomam",
"w5tmh5vadu4qcvrm2yp5kyoi":["ipox","yankee go home"],
"r2onmqsmif4e3jquyxvri7ve":["ipom","文"],
"sh2eqkwjfrn275ehw3ftvpam":"ipotential",
"mnby6wr6qk6tubsqkiluhrib":["ipohondriia","солодка Мівіна"],
"pmqkdue6vcvii7vmkqgdr25r":"ipofil",
"5amnpd3reg64d7t5zw2e2sgh":["ipona","ipona 🌻"],
"7f7rfvxpqqsdlf3guleu6ng2":["ipo","ipo"],
"o5fkjgbvi36cmjemfh72yixz":["ipodtouch0218","ipodtouch0218"],
"lehorbtusdnai7gfxq6asnl3":["ipo4ka","Ipo4ka.ua"],
"s6iljryg46ornyzr3ivbq3ad":"ipourwines",
"vmlk7zlzuombab3opvmc3jjr":["ipongjkbase","IpongJkBase🕊"],
"piszjut4x4h25a5cxigh3kdg":"ipofficial",
"hb7ixpf7xz4virbqoudlfjhh":["ipoxondrik","КушаЦ Подано "],
"yauie2qpwjyup7x6huaaobll":["ipoke","iPoke"],
"nwyviluquqh2oyc5t27gab5k":["ipos","IPOS"],
"st5fxayzildmvkmgagjw4wqe":["ipolarbear","iPolarBear"],
"qvcvhawiefyqav2cuf6u3svh":"iponikar",
"fvgkyslk6a2lfn545iery35n":"ipochocho",
"35wtladrzd2khypw3g3kg2av":["ipoltmarkus","Markus Ipolt "],
"o4da5sid45b2wds3gbosnhoy":["pripoldnica","Připołdnica"]
}
