{
"ixcghpz7h6ilgrhgmfxfo2vd":["99ispotato","99"],
"rmflciditaty3fffn53hdz2g":["acramjr","Acram Isper Jr."],
"de56i7lqpjh7g5apqz62pb74":["dersaadetvapurlari","dersaadet vapurlari kadrolu isportacisi"],
"tnsvacy757mrzbs3rt74kfai":["ingoisphording","Ingo E. Isphording "],
"axhrbmofnrnm27icuktlrgy6":["isparky","Sparky Fael"],
"gvvud4f3zp5t647xvthoptjd":["ispecter","ISpecter"],
"jmovfug4d3z77byxh7445cyt":["ispanieta","Nataliya Shpartak"],
"lltr5zmwxye4mahsayj3a23m":["ispod","인성팟탄"],
"yhouwiankkbauk66544olx5n":["ispan","Shaylyn Ispan"],
"fkfs6uhy6zvtiqpcrkwpew6s":["isphus","Arthur Scardua"],
"pxpcwtcmskvnzfaltry3mutk":["ispykenny","Kenny krosky "],
"wxrcpa5e44ru437fworaz2oh":["ispern","Hiromitsu Matsuoka"],
"d3qkhr5vdlu46aawlqk2fglo":["isputra","Putra"],
"sqyv7lurwfrguxsepmtihey5":["ispegi","Ang"],
"vut5ug2ezffmubcpdobopcon":"ispencer",
"apysevpfko7bhpxyd6l56iqv":["isp","Iain P"],
"bp2orzma7wr2zvbjpuzw72ch":["ispradlin","Isaac Spradlin "],
"ek5sxxyebg2i3p65zldv2j75":"ispeaknerd",
"6y6zdjcbc2gniyc75vmxdkfo":["ispamobjection","IspamObjection"],
"3iirma2rs5c6bge6rtfyeajw":["ispini","ispini"],
"r4ykbdjkkgijpycqasuqkpgr":"ispfox",
"due2i5gyjbk73d3lndtksnjv":["ispythesky","Lucas"],
"tu44k3jwc4ho2cmmgrfwhu5l":["ispy","Imagination"],
"66um5fqh5ewl3r4pjmi64swo":["ispyelli","Elli"],
"4xo34mar7u2ml6m2gv3to3f3":"isparta",
"6vrzidi456bizn4tadrsdaqr":"ispinox",
"l7zcmfip7ol6cv6befanysxi":["ispacemonki","iSpaceMonki"],
"pldazpnwrvkyp26n23kxwzwg":["ispepsharko","Ispep "],
"dfrizgrlhbfwaicn6677dagu":["ispeedtestos","iSpeedtestOS"],
"3vekv5lodiko67flt4nwecrl":["ispfo","isadora"],
"naz2ouvgsgenofw4rntrtxym":"ispack1107",
"wody5pfeukobmzq25725jiep":["ispotato","ispotato"],
"oioojs4lvtkjvqklgsx7hxi5":"isphoto",
"qtvpunno3bqi6ejewxapldfu":["ispeak2jah","Iam_ME🙎"],
"irmysldqvyko65gooagik63g":["ispor","Eris (cieloazul edición)"],
"ntgwob62xdhrsff4vljrhecq":["ispsyale","Yale ISPS"],
"2ucnx6ksv6bxa4366eudu3d3":["ispyanonymously","Katrina"],
"76dkzrrsbybuqehaavjgcuot":["ispjournal","International Studies Perspectives"],
"qdcn3urg7uysu6u2ui4kvh2u":["ispaul","Paul"],
"xzy6h5gnqcwvhqb34jgatkhv":["ispartofthe.lgbt","l' oeufs"],
"ef7qjktzfvs4ioqeb7lduh5c":["isp1481","HP"],
"3e2ggda4h6c45arxf3f2igs4":"isphal",
"slf57ty3pffgjtcf3q4tab5z":["isperfect79","Nobody "],
"tc5fmafbl4jvue5as4d7jnwv":"isperyr",
"w3u5l3bgt2d7z5xz6mqv2er2":"ispyrarts",
"itisdsjtrsh5jl2iy2f6m5am":["ispa-proteomics","Ignacio Ortea"],
"2zpvuh2b5ez65wnvnwf7aeyr":"ispine",
"2wy5dpypancyzexvidhk3qyf":["ispeakjive","Jeremy Something"],
"w4vtcfman2sssqnnnvidgybh":["ispuggo","Puggoberto "],
"cuv4zk4ykwirwoj7mxm56vz4":["ispa","ISPA - Internet Service Providers Austria"],
"ruhnjlr2e4owvr7mybujakly":["ispirit","Tha AranaLian"],
"et3ufhvj22r6adserydsm3pg":"ispago",
"c7o36letd2g2ut6wd7pxahlx":["isperia","Isperia"],
"23ztgs5v7l7qpfhsthfad7fu":["ispheo","ispheo"],
"dhbivcgdynlxjlocxvprla4o":"ispalko",
"padklbfyctr4ehskiqrkqm5a":["ispieth","Ines Benner-Spieth"],
"ah36maftcruidos4wtbr6dnm":"ispyamoose",
"twys5afmsp3o6oy4eufr74sb":["ispitundead","чи помер сьогодні путін?"],
"y2f7ke4wuxgzo4lnmlne333p":["ispijker","Ineke"],
"5lr62e6jepuykt3rivtv5oh4":["ispah","Ispah"],
"b56gifcs2fwlvxrl32tghuly":["loki-isp","Loki ISP"],
"wixdrosdikzoxvqt6n562zvx":["vitaispirata","Vita Ispirata"]
}
